fspinstance/__init__.py
jobshopinstance/__init__.py
jobshopinstance-0.5.dist-info/METADATA
jobshopinstance-0.5.dist-info/WHEEL
jobshopinstance-0.5.dist-info/top_level.txt
jobshopinstance-0.5.dist-info/RECORD
