Metadata-Version: 2.1
Name: jobshopinstance
Version: 0.5
Summary: Job Shop Instance Generator
Home-page: http://github.com/ericklarac/jobshopinstance
Author: Erick Lara C
Author-email: ericklarita@gmail.com
License: MIT
Platform: UNKNOWN
